{
  "date": "2026-05-05",
  "ticker": "CGIE",
  "holdings": [
    {
      "ticker": "ASML",
      "name": "ASML HOLDING NV COMMON STOCK EUR.09",
      "pct_net_assets": 0.0423,
      "shares": 62449.0
    },
    {
      "ticker": "TTE",
      "name": "TOTALENERGIES SE COMMON STOCK EUR2.5",
      "pct_net_assets": 0.0362,
      "shares": 807592.0
    },
    {
      "ticker": "CMQXX",
      "name": "CAPITAL GROUP CENTRAL CASH FUN CAPITAL GROUP CNTRL CSH M",
      "pct_net_assets": 0.0331,
      "shares": 679150.0
    },
    {
      "ticker": "TSM",
      "name": "TAIWAN SEMICONDUCTOR SP ADR ADR",
      "pct_net_assets": 0.0291,
      "shares": 148436.0
    },
    {
      "ticker": "AZN",
      "name": "ASTRAZENECA PLC COMMON STOCK USD.25",
      "pct_net_assets": 0.0271,
      "shares": 304033.0
    },
    {
      "ticker": "RWE",
      "name": "RWE AG COMMON STOCK",
      "pct_net_assets": 0.0243,
      "shares": 711846.0
    },
    {
      "ticker": "SAF",
      "name": "SAFRAN SA COMMON STOCK EUR.2",
      "pct_net_assets": 0.0236,
      "shares": 155822.0
    },
    {
      "ticker": "ENGI",
      "name": "ENGIE COMMON STOCK EUR1.0",
      "pct_net_assets": 0.0224,
      "shares": 1412992.0
    },
    {
      "ticker": "RR.",
      "name": "ROLLS ROYCE HOLDINGS PLC COMMON STOCK GBP.2",
      "pct_net_assets": 0.0216,
      "shares": 2732437.0
    },
    {
      "ticker": "SEB A",
      "name": "SKANDINAVISKA ENSKILDA BAN A COMMON STOCK SEK10.0",
      "pct_net_assets": 0.0213,
      "shares": 2278778.0
    },
    {
      "ticker": "UCG",
      "name": "UNICREDIT SPA COMMON STOCK",
      "pct_net_assets": 0.0193,
      "shares": 528612.0
    },
    {
      "ticker": "BA.",
      "name": "BAE SYSTEMS PLC COMMON STOCK GBP.025",
      "pct_net_assets": 0.0186,
      "shares": 1382371.0
    },
    {
      "ticker": "8058",
      "name": "MITSUBISHI CORP COMMON STOCK",
      "pct_net_assets": 0.0179,
      "shares": 1106100.0
    },
    {
      "ticker": "AIR",
      "name": "AIRBUS SE COMMON STOCK EUR1.0",
      "pct_net_assets": 0.0175,
      "shares": 174209.0
    },
    {
      "ticker": "388",
      "name": "HONG KONG EXCHANGES + CLEAR COMMON STOCK",
      "pct_net_assets": 0.017,
      "shares": 659500.0
    },
    {
      "ticker": "ABBN",
      "name": "ABB LTD REG COMMON STOCK CHF.12",
      "pct_net_assets": 0.0169,
      "shares": 346866.0
    },
    {
      "ticker": "ENX",
      "name": "EURONEXT NV COMMON STOCK EUR1.6",
      "pct_net_assets": 0.0169,
      "shares": 206074.0
    },
    {
      "ticker": "SAP",
      "name": "SAP SE COMMON STOCK",
      "pct_net_assets": 0.0167,
      "shares": 198214.0
    },
    {
      "ticker": "DSV",
      "name": "DSV A/S COMMON STOCK DKK1.0",
      "pct_net_assets": 0.0166,
      "shares": 149981.0
    },
    {
      "ticker": "IBE",
      "name": "IBERDROLA SA COMMON STOCK EUR.75",
      "pct_net_assets": 0.0166,
      "shares": 1486690.0
    },
    {
      "ticker": "8308",
      "name": "RESONA HOLDINGS INC COMMON STOCK",
      "pct_net_assets": 0.0157,
      "shares": 2628100.0
    },
    {
      "ticker": "8002",
      "name": "MARUBENI CORP COMMON STOCK",
      "pct_net_assets": 0.0153,
      "shares": 854000.0
    },
    {
      "ticker": "8035",
      "name": "TOKYO ELECTRON LTD COMMON STOCK",
      "pct_net_assets": 0.0151,
      "shares": 102800.0
    },
    {
      "ticker": "NESN",
      "name": "NESTLE SA REG COMMON STOCK CHF.1",
      "pct_net_assets": 0.0146,
      "shares": 300103.0
    },
    {
      "ticker": "HLMA",
      "name": "HALMA PLC COMMON STOCK GBP.1",
      "pct_net_assets": 0.0141,
      "shares": 472200.0
    },
    {
      "ticker": "1299",
      "name": "AIA GROUP LTD COMMON STOCK",
      "pct_net_assets": 0.014,
      "shares": 2607600.0
    },
    {
      "ticker": "D05",
      "name": "DBS GROUP HOLDINGS LTD COMMON STOCK",
      "pct_net_assets": 0.0133,
      "shares": 594000.0
    },
    {
      "ticker": "6501",
      "name": "HITACHI LTD COMMON STOCK",
      "pct_net_assets": 0.0132,
      "shares": 888600.0
    },
    {
      "ticker": "SAN",
      "name": "BANCO SANTANDER SA COMMON STOCK EUR.5",
      "pct_net_assets": 0.013,
      "shares": 2283169.0
    },
    {
      "ticker": "BATS",
      "name": "BRITISH AMERICAN TOBACCO PLC COMMON STOCK",
      "pct_net_assets": 0.0127,
      "shares": 443141.0
    },
    {
      "ticker": "NWG",
      "name": "NATWEST GROUP PLC COMMON STOCK GBP1.0769",
      "pct_net_assets": 0.0122,
      "shares": 3266410.0
    },
    {
      "ticker": "MUV2",
      "name": "MUENCHENER RUECKVER AG REG COMMON STOCK",
      "pct_net_assets": 0.0121,
      "shares": 41710.0
    },
    {
      "ticker": "SIE",
      "name": "SIEMENS AG REG COMMON STOCK",
      "pct_net_assets": 0.012,
      "shares": 84090.0
    },
    {
      "ticker": "A000660",
      "name": "SK HYNIX INC COMMON STOCK KRW5000.0",
      "pct_net_assets": 0.0118,
      "shares": 24582.0
    },
    {
      "ticker": "6861",
      "name": "KEYENCE CORP COMMON STOCK",
      "pct_net_assets": 0.0117,
      "shares": 49500.0
    },
    {
      "ticker": "OR",
      "name": "L OREAL COMMON STOCK EUR.2",
      "pct_net_assets": 0.0117,
      "shares": 57041.0
    },
    {
      "ticker": "SU",
      "name": "SCHNEIDER ELECTRIC SE COMMON STOCK EUR4.0",
      "pct_net_assets": 0.0116,
      "shares": 77856.0
    },
    {
      "ticker": "ITX",
      "name": "INDUSTRIA DE DISENO TEXTIL COMMON STOCK EUR.03",
      "pct_net_assets": 0.0114,
      "shares": 405180.0
    },
    {
      "ticker": "DB1",
      "name": "DEUTSCHE BOERSE AG COMMON STOCK",
      "pct_net_assets": 0.0113,
      "shares": 76002.0
    },
    {
      "ticker": "BBVA",
      "name": "BANCO BILBAO VIZCAYA ARGENTA COMMON STOCK EUR.49",
      "pct_net_assets": 0.0112,
      "shares": 1099806.0
    },
    {
      "ticker": "AMS",
      "name": "AMADEUS IT GROUP SA COMMON STOCK EUR.01",
      "pct_net_assets": 0.0111,
      "shares": 406798.0
    },
    {
      "ticker": "8001",
      "name": "ITOCHU CORP COMMON STOCK",
      "pct_net_assets": 0.0111,
      "shares": 1793000.0
    },
    {
      "ticker": "4519",
      "name": "CHUGAI PHARMACEUTICAL CO LTD COMMON STOCK",
      "pct_net_assets": 0.0107,
      "shares": 419400.0
    },
    {
      "ticker": "6758",
      "name": "SONY GROUP CORP COMMON STOCK",
      "pct_net_assets": 0.0107,
      "shares": 1104400.0
    },
    {
      "ticker": "GLEN",
      "name": "GLENCORE PLC COMMON STOCK USD.01",
      "pct_net_assets": 0.0104,
      "shares": 2810139.0
    },
    {
      "ticker": "B",
      "name": "BARRICK MINING CORP COMMON STOCK",
      "pct_net_assets": 0.0102,
      "shares": 546868.0
    },
    {
      "ticker": "SHOP",
      "name": "SHOPIFY INC   CLASS A COMMON STOCK",
      "pct_net_assets": 0.0102,
      "shares": 164018.0
    },
    {
      "ticker": "IMB",
      "name": "IMPERIAL BRANDS PLC COMMON STOCK GBP.1",
      "pct_net_assets": 0.01,
      "shares": 538853.0
    },
    {
      "ticker": "NOVOB",
      "name": "NOVO NORDISK A/S B COMMON STOCK DKK.1",
      "pct_net_assets": 0.01,
      "shares": 465008.0
    },
    {
      "ticker": "RYAAY",
      "name": "RYANAIR HOLDINGS PLC SP ADR ADR",
      "pct_net_assets": 0.0098,
      "shares": 378366.0
    },
    {
      "ticker": "4063",
      "name": "SHIN ETSU CHEMICAL CO LTD COMMON STOCK",
      "pct_net_assets": 0.0097,
      "shares": 439000.0
    },
    {
      "ticker": "BNP",
      "name": "BNP PARIBAS COMMON STOCK EUR2.0",
      "pct_net_assets": 0.0092,
      "shares": 183520.0
    },
    {
      "ticker": "6367",
      "name": "DAIKIN INDUSTRIES LTD COMMON STOCK",
      "pct_net_assets": 0.0092,
      "shares": 130300.0
    },
    {
      "ticker": "STAN",
      "name": "STANDARD CHARTERED PLC COMMON STOCK USD.5",
      "pct_net_assets": 0.0092,
      "shares": 740052.0
    },
    {
      "ticker": "7741",
      "name": "HOYA CORP COMMON STOCK",
      "pct_net_assets": 0.0091,
      "shares": 105900.0
    },
    {
      "ticker": "ABI",
      "name": "ANHEUSER BUSCH INBEV SA/NV COMMON STOCK",
      "pct_net_assets": 0.009,
      "shares": 249488.0
    },
    {
      "ticker": "6098",
      "name": "RECRUIT HOLDINGS CO LTD COMMON STOCK",
      "pct_net_assets": 0.009,
      "shares": 395400.0
    },
    {
      "ticker": "EL",
      "name": "ESSILORLUXOTTICA COMMON STOCK EUR.18",
      "pct_net_assets": 0.0087,
      "shares": 88429.0
    },
    {
      "ticker": "MC",
      "name": "LVMH MOET HENNESSY LOUIS VUI COMMON STOCK EUR.3",
      "pct_net_assets": 0.0087,
      "shares": 34328.0
    },
    {
      "ticker": "BN",
      "name": "DANONE COMMON STOCK EUR.25",
      "pct_net_assets": 0.0083,
      "shares": 224319.0
    },
    {
      "ticker": "SGO",
      "name": "COMPAGNIE DE SAINT GOBAIN COMMON STOCK EUR4.0",
      "pct_net_assets": 0.0082,
      "shares": 191990.0
    },
    {
      "ticker": "MTX",
      "name": "MTU AERO ENGINES AG COMMON STOCK",
      "pct_net_assets": 0.0082,
      "shares": 51183.0
    },
    {
      "ticker": "KSP",
      "name": "KINGSPAN GROUP PLC COMMON STOCK EUR.13",
      "pct_net_assets": 0.0079,
      "shares": 176327.0
    },
    {
      "ticker": "ANTO",
      "name": "ANTOFAGASTA PLC COMMON STOCK",
      "pct_net_assets": 0.0078,
      "shares": 331697.0
    },
    {
      "ticker": "700",
      "name": "TENCENT HOLDINGS LTD COMMON STOCK HKD.00002",
      "pct_net_assets": 0.0074,
      "shares": 250100.0
    },
    {
      "ticker": "6503",
      "name": "MITSUBISHI ELECTRIC CORP COMMON STOCK",
      "pct_net_assets": 0.0072,
      "shares": 384000.0
    },
    {
      "ticker": "6146",
      "name": "DISCO CORP COMMON STOCK",
      "pct_net_assets": 0.007,
      "shares": 31000.0
    },
    {
      "ticker": "6702",
      "name": "FUJITSU LIMITED COMMON STOCK",
      "pct_net_assets": 0.0067,
      "shares": 702000.0
    },
    {
      "ticker": "LSEG",
      "name": "LONDON STOCK EXCHANGE GROUP COMMON STOCK GBP.06918605",
      "pct_net_assets": 0.0065,
      "shares": 101854.0
    },
    {
      "ticker": "RHM",
      "name": "RHEINMETALL AG COMMON STOCK",
      "pct_net_assets": 0.0053,
      "shares": 6700.0
    },
    {
      "ticker": "MELI",
      "name": "MERCADOLIBRE INC COMMON STOCK USD.001",
      "pct_net_assets": 0.0051,
      "shares": 5776.0
    },
    {
      "ticker": "ONC",
      "name": "BEONE MEDICINES LTD ADR ADR USD.0001",
      "pct_net_assets": 0.005,
      "shares": 34773.0
    },
    {
      "ticker": "7974",
      "name": "NINTENDO CO LTD COMMON STOCK",
      "pct_net_assets": 0.0046,
      "shares": 195000.0
    }
  ]
}