{
  "date": "2026-04-28",
  "ticker": "CGUS",
  "prior_date": "2026-04-27",
  "diff": [
    {
      "ticker": "AAPL",
      "name": "APPLE INC COMMON STOCK USD.00001",
      "status": "unchanged",
      "shares_today": 1140849.0,
      "shares_prior": 1140849.0,
      "shares_pct_change": 0.0,
      "shares_5d_change": 0.4097,
      "shares_10d_change": 1.0944,
      "shares_30d_change": null,
      "pct_net_assets_today": 0.03,
      "pct_net_assets_prior": 0.0304,
      "pct_net_assets_change": -0.0004
    },
    {
      "ticker": "ABBV",
      "name": "ABBVIE INC COMMON STOCK USD.01",
      "status": "unchanged",
      "shares_today": 291933.0,
      "shares_prior": 291933.0,
      "shares_pct_change": 0.0,
      "shares_5d_change": 0.4045,
      "shares_10d_change": 1.0803,
      "shares_30d_change": null,
      "pct_net_assets_today": 0.0057,
      "pct_net_assets_prior": 0.0057,
      "pct_net_assets_change": 0.0
    },
    {
      "ticker": "ABT",
      "name": "ABBOTT LABORATORIES COMMON STOCK",
      "status": "unchanged",
      "shares_today": 761109.0,
      "shares_prior": 761109.0,
      "shares_pct_change": 0.0,
      "shares_5d_change": 0.4072,
      "shares_10d_change": 1.0878,
      "shares_30d_change": null,
      "pct_net_assets_today": 0.0069,
      "pct_net_assets_prior": 0.0068,
      "pct_net_assets_change": 0.0001
    },
    {
      "ticker": "ACN",
      "name": "ACCENTURE PLC CL A COMMON STOCK USD.0000225",
      "status": "unchanged",
      "shares_today": 273934.0,
      "shares_prior": 273934.0,
      "shares_pct_change": 0.0,
      "shares_5d_change": 0.4131,
      "shares_10d_change": 1.1035,
      "shares_30d_change": null,
      "pct_net_assets_today": 0.0048,
      "pct_net_assets_prior": 0.0048,
      "pct_net_assets_change": 0.0
    },
    {
      "ticker": "ADP",
      "name": "AUTOMATIC DATA PROCESSING COMMON STOCK USD.1",
      "status": "unchanged",
      "shares_today": 581685.0,
      "shares_prior": 581685.0,
      "shares_pct_change": 0.0,
      "shares_5d_change": 0.4145,
      "shares_10d_change": 1.1072,
      "shares_30d_change": null,
      "pct_net_assets_today": 0.0113,
      "pct_net_assets_prior": 0.0112,
      "pct_net_assets_change": 0.0001
    },
    {
      "ticker": "AMAT",
      "name": "APPLIED MATERIALS INC COMMON STOCK USD.01",
      "status": "unchanged",
      "shares_today": 612052.0,
      "shares_prior": 612052.0,
      "shares_pct_change": 0.0,
      "shares_5d_change": 0.41,
      "shares_10d_change": 1.0951,
      "shares_30d_change": null,
      "pct_net_assets_today": 0.0244,
      "pct_net_assets_prior": 0.0251,
      "pct_net_assets_change": -0.0007
    },
    {
      "ticker": "AMZN",
      "name": "AMAZON.COM INC COMMON STOCK USD.01",
      "status": "unchanged",
      "shares_today": 2057003.0,
      "shares_prior": 2057003.0,
      "shares_pct_change": 0.0,
      "shares_5d_change": 0.409,
      "shares_10d_change": 1.0925,
      "shares_30d_change": null,
      "pct_net_assets_today": 0.0528,
      "pct_net_assets_prior": 0.0534,
      "pct_net_assets_change": -0.0006
    },
    {
      "ticker": "ANET",
      "name": "ARISTA NETWORKS INC COMMON STOCK USD.0001",
      "status": "unchanged",
      "shares_today": 381962.0,
      "shares_prior": 381962.0,
      "shares_pct_change": 0.0,
      "shares_5d_change": 0.4122,
      "shares_10d_change": 1.1011,
      "shares_30d_change": null,
      "pct_net_assets_today": 0.0065,
      "pct_net_assets_prior": 0.0066,
      "pct_net_assets_change": -0.0001
    },
    {
      "ticker": "APD",
      "name": "AIR PRODUCTS + CHEMICALS INC COMMON STOCK USD1.0",
      "status": "unchanged",
      "shares_today": 357255.0,
      "shares_prior": 357255.0,
      "shares_pct_change": 0.0,
      "shares_5d_change": 0.4132,
      "shares_10d_change": 1.1037,
      "shares_30d_change": null,
      "pct_net_assets_today": 0.0106,
      "pct_net_assets_prior": 0.0106,
      "pct_net_assets_change": 0.0
    },
    {
      "ticker": "APH",
      "name": "AMPHENOL CORP CL A COMMON STOCK USD.001",
      "status": "unchanged",
      "shares_today": 1017913.0,
      "shares_prior": 1017913.0,
      "shares_pct_change": 0.0,
      "shares_5d_change": 0.4109,
      "shares_10d_change": 1.0975,
      "shares_30d_change": null,
      "pct_net_assets_today": 0.0149,
      "pct_net_assets_prior": 0.015,
      "pct_net_assets_change": -0.0001
    },
    {
      "ticker": "AVGO",
      "name": "BROADCOM INC COMMON STOCK",
      "status": "unchanged",
      "shares_today": 1544385.0,
      "shares_prior": 1544385.0,
      "shares_pct_change": 0.0,
      "shares_5d_change": 0.411,
      "shares_10d_change": 1.0978,
      "shares_30d_change": null,
      "pct_net_assets_today": 0.0635,
      "pct_net_assets_prior": 0.0642,
      "pct_net_assets_change": -0.0007
    },
    {
      "ticker": "BATS",
      "name": "BRITISH AMERICAN TOBACCO PLC COMMON STOCK",
      "status": "unchanged",
      "shares_today": 3098262.0,
      "shares_prior": 3098262.0,
      "shares_pct_change": 0.0,
      "shares_5d_change": 0.4097,
      "shares_10d_change": 1.0944,
      "shares_30d_change": null,
      "pct_net_assets_today": 0.0175,
      "pct_net_assets_prior": 0.0177,
      "pct_net_assets_change": -0.0002
    },
    {
      "ticker": "BKR",
      "name": "BAKER HUGHES CO COMMON STOCK USD.0001",
      "status": "unchanged",
      "shares_today": 1793439.0,
      "shares_prior": 1793439.0,
      "shares_pct_change": 0.0,
      "shares_5d_change": 0.4088,
      "shares_10d_change": 1.0918,
      "shares_30d_change": null,
      "pct_net_assets_today": 0.0121,
      "pct_net_assets_prior": 0.0122,
      "pct_net_assets_change": -0.0001
    },
    {
      "ticker": "BLK",
      "name": "BLACKROCK INC COMMON STOCK USD.01",
      "status": "unchanged",
      "shares_today": 157743.0,
      "shares_prior": 157743.0,
      "shares_pct_change": 0.0,
      "shares_5d_change": 0.4055,
      "shares_10d_change": 1.083,
      "shares_30d_change": null,
      "pct_net_assets_today": 0.0164,
      "pct_net_assets_prior": 0.0162,
      "pct_net_assets_change": 0.0002
    },
    {
      "ticker": "CARR",
      "name": "CARRIER GLOBAL CORP COMMON STOCK USD.01",
      "status": "unchanged",
      "shares_today": 2064822.0,
      "shares_prior": 2064822.0,
      "shares_pct_change": 0.0,
      "shares_5d_change": 0.4098,
      "shares_10d_change": 1.0948,
      "shares_30d_change": null,
      "pct_net_assets_today": 0.0126,
      "pct_net_assets_prior": 0.0124,
      "pct_net_assets_change": 0.0002
    },
    {
      "ticker": "CAT",
      "name": "CATERPILLAR INC COMMON STOCK USD1.0",
      "status": "unchanged",
      "shares_today": 94664.0,
      "shares_prior": 94664.0,
      "shares_pct_change": 0.0,
      "shares_5d_change": 0.4158,
      "shares_10d_change": 1.1108,
      "shares_30d_change": null,
      "pct_net_assets_today": 0.0077,
      "pct_net_assets_prior": 0.0077,
      "pct_net_assets_change": 0.0
    },
    {
      "ticker": "CB",
      "name": "CHUBB LTD COMMON STOCK",
      "status": "unchanged",
      "shares_today": 191259.0,
      "shares_prior": 191259.0,
      "shares_pct_change": 0.0,
      "shares_5d_change": 0.4116,
      "shares_10d_change": 1.0995,
      "shares_30d_change": null,
      "pct_net_assets_today": 0.0061,
      "pct_net_assets_prior": 0.0061,
      "pct_net_assets_change": 0.0
    },
    {
      "ticker": "CMQXX",
      "name": "CAPITAL GROUP CENTRAL CASH FUN CAPITAL GROUP CNTRL CSH M",
      "status": "changed",
      "shares_today": 947668.09,
      "shares_prior": 945577.88,
      "shares_pct_change": 0.2211,
      "shares_5d_change": 2.2189,
      "shares_10d_change": 4.3602,
      "shares_30d_change": null,
      "pct_net_assets_today": 0.0093,
      "pct_net_assets_prior": 0.0093,
      "pct_net_assets_change": 0.0
    },
    {
      "ticker": "CNP",
      "name": "CENTERPOINT ENERGY INC COMMON STOCK USD.01",
      "status": "unchanged",
      "shares_today": 1918199.0,
      "shares_prior": 1918199.0,
      "shares_pct_change": 0.0,
      "shares_5d_change": 0.4104,
      "shares_10d_change": 1.0962,
      "shares_30d_change": null,
      "pct_net_assets_today": 0.0081,
      "pct_net_assets_prior": 0.008,
      "pct_net_assets_change": 0.0001
    },
    {
      "ticker": "CNQ",
      "name": "CANADIAN NATURAL RESOURCES COMMON STOCK",
      "status": "unchanged",
      "shares_today": 3385606.0,
      "shares_prior": 3385606.0,
      "shares_pct_change": 0.0,
      "shares_5d_change": 0.4098,
      "shares_10d_change": 1.0947,
      "shares_30d_change": null,
      "pct_net_assets_today": 0.015,
      "pct_net_assets_prior": 0.0148,
      "pct_net_assets_change": 0.0002
    },
    {
      "ticker": "CRM",
      "name": "SALESFORCE INC COMMON STOCK USD.001",
      "status": "unchanged",
      "shares_today": 296340.0,
      "shares_prior": 296340.0,
      "shares_pct_change": 0.0,
      "shares_5d_change": 0.4151,
      "shares_10d_change": 1.1089,
      "shares_30d_change": null,
      "pct_net_assets_today": 0.0053,
      "pct_net_assets_prior": 0.0052,
      "pct_net_assets_change": 0.0001
    },
    {
      "ticker": "CSCO",
      "name": "CISCO SYSTEMS INC COMMON STOCK USD.001",
      "status": "unchanged",
      "shares_today": 1560617.0,
      "shares_prior": 1560617.0,
      "shares_pct_change": 0.0,
      "shares_5d_change": 0.4098,
      "shares_10d_change": 1.0948,
      "shares_30d_change": null,
      "pct_net_assets_today": 0.0135,
      "pct_net_assets_prior": 0.0137,
      "pct_net_assets_change": -0.0002
    },
    {
      "ticker": "CTSH",
      "name": "COGNIZANT TECH SOLUTIONS A COMMON STOCK USD.01",
      "status": "unchanged",
      "shares_today": 1009273.0,
      "shares_prior": 1009273.0,
      "shares_pct_change": 0.0,
      "shares_5d_change": 0.4095,
      "shares_10d_change": 1.0938,
      "shares_30d_change": null,
      "pct_net_assets_today": 0.0054,
      "pct_net_assets_prior": 0.0055,
      "pct_net_assets_change": -0.0001
    },
    {
      "ticker": "CVS",
      "name": "CVS HEALTH CORP COMMON STOCK USD.01",
      "status": "unchanged",
      "shares_today": 418486.0,
      "shares_prior": 418486.0,
      "shares_pct_change": 0.0,
      "shares_5d_change": 0.4115,
      "shares_10d_change": 1.0992,
      "shares_30d_change": null,
      "pct_net_assets_today": 0.0032,
      "pct_net_assets_prior": 0.0032,
      "pct_net_assets_change": 0.0
    },
    {
      "ticker": "D",
      "name": "DOMINION ENERGY INC COMMON STOCK",
      "status": "unchanged",
      "shares_today": 1297608.0,
      "shares_prior": 1297608.0,
      "shares_pct_change": 0.0,
      "shares_5d_change": 0.4095,
      "shares_10d_change": 1.0938,
      "shares_30d_change": null,
      "pct_net_assets_today": 0.008,
      "pct_net_assets_prior": 0.008,
      "pct_net_assets_change": 0.0
    },
    {
      "ticker": "ENTG",
      "name": "ENTEGRIS INC COMMON STOCK USD.01",
      "status": "unchanged",
      "shares_today": 797511.0,
      "shares_prior": 797511.0,
      "shares_pct_change": 0.0,
      "shares_5d_change": 0.4072,
      "shares_10d_change": 1.0875,
      "shares_30d_change": null,
      "pct_net_assets_today": 0.0123,
      "pct_net_assets_prior": 0.0122,
      "pct_net_assets_change": 0.0001
    },
    {
      "ticker": "EQIX",
      "name": "EQUINIX INC REIT USD.001",
      "status": "unchanged",
      "shares_today": 72731.0,
      "shares_prior": 72731.0,
      "shares_pct_change": 0.0,
      "shares_5d_change": 0.4059,
      "shares_10d_change": 1.0841,
      "shares_30d_change": null,
      "pct_net_assets_today": 0.0078,
      "pct_net_assets_prior": 0.0079,
      "pct_net_assets_change": -0.0001
    },
    {
      "ticker": "FIS",
      "name": "FIDELITY NATIONAL INFO SERV COMMON STOCK USD.01",
      "status": "unchanged",
      "shares_today": 1459659.0,
      "shares_prior": 1459659.0,
      "shares_pct_change": 0.0,
      "shares_5d_change": 0.4112,
      "shares_10d_change": 1.0985,
      "shares_30d_change": null,
      "pct_net_assets_today": 0.0065,
      "pct_net_assets_prior": 0.0066,
      "pct_net_assets_change": -0.0001
    },
    {
      "ticker": "GE",
      "name": "GENERAL ELECTRIC COMMON STOCK USD.01",
      "status": "unchanged",
      "shares_today": 428677.0,
      "shares_prior": 428677.0,
      "shares_pct_change": 0.0,
      "shares_5d_change": 0.4132,
      "shares_10d_change": 1.1038,
      "shares_30d_change": null,
      "pct_net_assets_today": 0.012,
      "pct_net_assets_prior": 0.012,
      "pct_net_assets_change": 0.0
    },
    {
      "ticker": "GFL",
      "name": "GFL ENVIRONMENTAL INC SUB VT COMMON STOCK",
      "status": "unchanged",
      "shares_today": 2407543.0,
      "shares_prior": 2407543.0,
      "shares_pct_change": 0.0,
      "shares_5d_change": 0.4108,
      "shares_10d_change": 1.0972,
      "shares_30d_change": null,
      "pct_net_assets_today": 0.0094,
      "pct_net_assets_prior": 0.0096,
      "pct_net_assets_change": -0.0002
    },
    {
      "ticker": "GLW",
      "name": "CORNING INC COMMON STOCK USD.5",
      "status": "unchanged",
      "shares_today": 377698.0,
      "shares_prior": 377698.0,
      "shares_pct_change": 0.0,
      "shares_5d_change": 0.4169,
      "shares_10d_change": 1.1137,
      "shares_30d_change": null,
      "pct_net_assets_today": 0.0062,
      "pct_net_assets_prior": 0.0065,
      "pct_net_assets_change": -0.0003
    },
    {
      "ticker": "GOOG",
      "name": "ALPHABET INC CL C COMMON STOCK USD.001",
      "status": "unchanged",
      "shares_today": 575467.0,
      "shares_prior": 575467.0,
      "shares_pct_change": 0.0,
      "shares_5d_change": 0.4104,
      "shares_10d_change": 1.0962,
      "shares_30d_change": null,
      "pct_net_assets_today": 0.0197,
      "pct_net_assets_prior": 0.0194,
      "pct_net_assets_change": 0.0003
    },
    {
      "ticker": "GOOGL",
      "name": "ALPHABET INC CL A COMMON STOCK USD.001",
      "status": "unchanged",
      "shares_today": 922462.0,
      "shares_prior": 922462.0,
      "shares_pct_change": 0.0,
      "shares_5d_change": 0.4107,
      "shares_10d_change": 1.097,
      "shares_30d_change": null,
      "pct_net_assets_today": 0.0318,
      "pct_net_assets_prior": 0.0312,
      "pct_net_assets_change": 0.0006
    },
    {
      "ticker": "GS",
      "name": "GOLDMAN SACHS GROUP INC COMMON STOCK USD.01",
      "status": "unchanged",
      "shares_today": 61910.0,
      "shares_prior": 61910.0,
      "shares_pct_change": 0.0,
      "shares_5d_change": 0.3973,
      "shares_10d_change": 1.0611,
      "shares_30d_change": null,
      "pct_net_assets_today": 0.0057,
      "pct_net_assets_prior": 0.0056,
      "pct_net_assets_change": 0.0001
    },
    {
      "ticker": "HD",
      "name": "HOME DEPOT INC COMMON STOCK USD.05",
      "status": "unchanged",
      "shares_today": 273154.0,
      "shares_prior": 273154.0,
      "shares_pct_change": 0.0,
      "shares_5d_change": 0.4143,
      "shares_10d_change": 1.1067,
      "shares_30d_change": null,
      "pct_net_assets_today": 0.0089,
      "pct_net_assets_prior": 0.009,
      "pct_net_assets_change": -0.0001
    },
    {
      "ticker": "HON",
      "name": "HONEYWELL INTERNATIONAL INC COMMON STOCK USD1.0",
      "status": "unchanged",
      "shares_today": 312857.0,
      "shares_prior": 312857.0,
      "shares_pct_change": 0.0,
      "shares_5d_change": 0.4089,
      "shares_10d_change": 1.0922,
      "shares_30d_change": null,
      "pct_net_assets_today": 0.0065,
      "pct_net_assets_prior": 0.0066,
      "pct_net_assets_change": -0.0001
    },
    {
      "ticker": "IP",
      "name": "INTERNATIONAL PAPER CO COMMON STOCK USD1.0",
      "status": "unchanged",
      "shares_today": 1784253.0,
      "shares_prior": 1784253.0,
      "shares_pct_change": 0.0,
      "shares_5d_change": 0.0,
      "shares_10d_change": 0.0,
      "shares_30d_change": null,
      "pct_net_assets_today": 0.0057,
      "pct_net_assets_prior": 0.0057,
      "pct_net_assets_change": 0.0
    },
    {
      "ticker": "IR",
      "name": "INGERSOLL RAND INC COMMON STOCK USD.01",
      "status": "unchanged",
      "shares_today": 827372.0,
      "shares_prior": 827372.0,
      "shares_pct_change": 0.0,
      "shares_5d_change": 0.4103,
      "shares_10d_change": 1.096,
      "shares_30d_change": null,
      "pct_net_assets_today": 0.0068,
      "pct_net_assets_prior": 0.0068,
      "pct_net_assets_change": 0.0
    },
    {
      "ticker": "JPM",
      "name": "JPMORGAN CHASE + CO COMMON STOCK USD1.0",
      "status": "unchanged",
      "shares_today": 701738.0,
      "shares_prior": 701738.0,
      "shares_pct_change": 0.0,
      "shares_5d_change": 0.4137,
      "shares_10d_change": 1.1051,
      "shares_30d_change": null,
      "pct_net_assets_today": 0.0215,
      "pct_net_assets_prior": 0.0213,
      "pct_net_assets_change": 0.0002
    },
    {
      "ticker": "LIN",
      "name": "LINDE PLC COMMON STOCK",
      "status": "unchanged",
      "shares_today": 285716.0,
      "shares_prior": 285716.0,
      "shares_pct_change": 0.0,
      "shares_5d_change": 0.4133,
      "shares_10d_change": 1.104,
      "shares_30d_change": null,
      "pct_net_assets_today": 0.0143,
      "pct_net_assets_prior": 0.0143,
      "pct_net_assets_change": 0.0
    },
    {
      "ticker": "LLY",
      "name": "ELI LILLY + CO COMMON STOCK",
      "status": "unchanged",
      "shares_today": 352299.0,
      "shares_prior": 352299.0,
      "shares_pct_change": 0.0,
      "shares_5d_change": 0.405,
      "shares_10d_change": 1.0817,
      "shares_30d_change": null,
      "pct_net_assets_today": 0.0301,
      "pct_net_assets_prior": 0.0306,
      "pct_net_assets_change": -0.0005
    },
    {
      "ticker": "MA",
      "name": "MASTERCARD INC   A COMMON STOCK USD.0001",
      "status": "unchanged",
      "shares_today": 391576.0,
      "shares_prior": 391576.0,
      "shares_pct_change": 0.0,
      "shares_5d_change": 0.4147,
      "shares_10d_change": 1.1077,
      "shares_30d_change": null,
      "pct_net_assets_today": 0.0195,
      "pct_net_assets_prior": 0.0194,
      "pct_net_assets_change": 0.0001
    },
    {
      "ticker": "MDLZ",
      "name": "MONDELEZ INTERNATIONAL INC A COMMON STOCK",
      "status": "unchanged",
      "shares_today": 1020126.0,
      "shares_prior": 1020126.0,
      "shares_pct_change": 0.0,
      "shares_5d_change": 0.41,
      "shares_10d_change": 1.0951,
      "shares_30d_change": null,
      "pct_net_assets_today": 0.0058,
      "pct_net_assets_prior": 0.0058,
      "pct_net_assets_change": 0.0
    },
    {
      "ticker": "META",
      "name": "META PLATFORMS INC CLASS A COMMON STOCK USD.000006",
      "status": "unchanged",
      "shares_today": 527395.0,
      "shares_prior": 527395.0,
      "shares_pct_change": 0.0,
      "shares_5d_change": 0.4105,
      "shares_10d_change": 1.0965,
      "shares_30d_change": null,
      "pct_net_assets_today": 0.0352,
      "pct_net_assets_prior": 0.035,
      "pct_net_assets_change": 0.0002
    },
    {
      "ticker": "MRSH",
      "name": "MARSH + MCLENNAN COS COMMON STOCK USD1.0",
      "status": "unchanged",
      "shares_today": 332403.0,
      "shares_prior": 332403.0,
      "shares_pct_change": 0.0,
      "shares_5d_change": 0.4145,
      "shares_10d_change": 1.1072,
      "shares_30d_change": null,
      "pct_net_assets_today": 0.0056,
      "pct_net_assets_prior": 0.0056,
      "pct_net_assets_change": 0.0
    },
    {
      "ticker": "MSFT",
      "name": "MICROSOFT CORP COMMON STOCK USD.00000625",
      "status": "unchanged",
      "shares_today": 1477062.0,
      "shares_prior": 1477062.0,
      "shares_pct_change": 0.0,
      "shares_5d_change": 0.4077,
      "shares_10d_change": 1.088,
      "shares_30d_change": null,
      "pct_net_assets_today": 0.0617,
      "pct_net_assets_prior": 0.0617,
      "pct_net_assets_change": 0.0
    },
    {
      "ticker": "NFLX",
      "name": "NETFLIX INC COMMON STOCK USD.001",
      "status": "unchanged",
      "shares_today": 1121221.0,
      "shares_prior": 1121221.0,
      "shares_pct_change": 0.0,
      "shares_5d_change": 0.4081,
      "shares_10d_change": 1.09,
      "shares_30d_change": null,
      "pct_net_assets_today": 0.0101,
      "pct_net_assets_prior": 0.0102,
      "pct_net_assets_change": -0.0001
    },
    {
      "ticker": "NVDA",
      "name": "NVIDIA CORP COMMON STOCK USD.001",
      "status": "unchanged",
      "shares_today": 3495616.0,
      "shares_prior": 3495616.0,
      "shares_pct_change": 0.0,
      "shares_5d_change": 0.4096,
      "shares_10d_change": 1.0941,
      "shares_30d_change": null,
      "pct_net_assets_today": 0.0745,
      "pct_net_assets_prior": 0.0716,
      "pct_net_assets_change": 0.0029
    },
    {
      "ticker": "ORCL",
      "name": "ORACLE CORP COMMON STOCK USD.01",
      "status": "unchanged",
      "shares_today": 374058.0,
      "shares_prior": 374058.0,
      "shares_pct_change": 0.0,
      "shares_5d_change": 0.4077,
      "shares_10d_change": 1.0891,
      "shares_30d_change": null,
      "pct_net_assets_today": 0.0064,
      "pct_net_assets_prior": 0.0064,
      "pct_net_assets_change": 0.0
    },
    {
      "ticker": "PGR",
      "name": "PROGRESSIVE CORP COMMON STOCK USD1.0",
      "status": "unchanged",
      "shares_today": 356456.0,
      "shares_prior": 356456.0,
      "shares_pct_change": 0.0,
      "shares_5d_change": 0.4141,
      "shares_10d_change": 1.1062,
      "shares_30d_change": null,
      "pct_net_assets_today": 0.0071,
      "pct_net_assets_prior": 0.007,
      "pct_net_assets_change": 0.0001
    },
    {
      "ticker": "PM",
      "name": "PHILIP MORRIS INTERNATIONAL COMMON STOCK",
      "status": "unchanged",
      "shares_today": 529016.0,
      "shares_prior": 529016.0,
      "shares_pct_change": 0.0,
      "shares_5d_change": 0.4092,
      "shares_10d_change": 1.0931,
      "shares_30d_change": null,
      "pct_net_assets_today": 0.0084,
      "pct_net_assets_prior": 0.0085,
      "pct_net_assets_change": -0.0001
    },
    {
      "ticker": "PNC",
      "name": "PNC FINANCIAL SERVICES GROUP COMMON STOCK USD5.0",
      "status": "unchanged",
      "shares_today": 283998.0,
      "shares_prior": 283998.0,
      "shares_pct_change": 0.0,
      "shares_5d_change": 0.4158,
      "shares_10d_change": 1.1108,
      "shares_30d_change": null,
      "pct_net_assets_today": 0.0062,
      "pct_net_assets_prior": 0.0061,
      "pct_net_assets_change": 0.0001
    },
    {
      "ticker": "RCL",
      "name": "ROYAL CARIBBEAN CRUISES LTD COMMON STOCK USD.01",
      "status": "unchanged",
      "shares_today": 313097.0,
      "shares_prior": 313097.0,
      "shares_pct_change": 0.0,
      "shares_5d_change": 0.4086,
      "shares_10d_change": 1.0913,
      "shares_30d_change": null,
      "pct_net_assets_today": 0.008,
      "pct_net_assets_prior": 0.0082,
      "pct_net_assets_change": -0.0002
    },
    {
      "ticker": "RTX",
      "name": "RTX CORP COMMON STOCK USD1.0",
      "status": "unchanged",
      "shares_today": 1148214.0,
      "shares_prior": 1148214.0,
      "shares_pct_change": 0.0,
      "shares_5d_change": 0.4114,
      "shares_10d_change": 1.0988,
      "shares_30d_change": null,
      "pct_net_assets_today": 0.0196,
      "pct_net_assets_prior": 0.0197,
      "pct_net_assets_change": -0.0001
    },
    {
      "ticker": "SBUX",
      "name": "STARBUCKS CORP COMMON STOCK USD.001",
      "status": "unchanged",
      "shares_today": 1653870.0,
      "shares_prior": 1653870.0,
      "shares_pct_change": 0.0,
      "shares_5d_change": 0.4105,
      "shares_10d_change": 1.0966,
      "shares_30d_change": null,
      "pct_net_assets_today": 0.0159,
      "pct_net_assets_prior": 0.0161,
      "pct_net_assets_change": -0.0002
    },
    {
      "ticker": "STX",
      "name": "SEAGATE TECHNOLOGY HOLDINGS COMMON STOCK USD.00001",
      "status": "unchanged",
      "shares_today": 255157.0,
      "shares_prior": 255157.0,
      "shares_pct_change": 0.0,
      "shares_5d_change": 0.4049,
      "shares_10d_change": 1.0815,
      "shares_30d_change": null,
      "pct_net_assets_today": 0.015,
      "pct_net_assets_prior": 0.0147,
      "pct_net_assets_change": 0.0003
    },
    {
      "ticker": "TMO",
      "name": "THERMO FISHER SCIENTIFIC INC COMMON STOCK USD1.0",
      "status": "unchanged",
      "shares_today": 110746.0,
      "shares_prior": 110746.0,
      "shares_pct_change": 0.0,
      "shares_5d_change": 0.3998,
      "shares_10d_change": 1.0678,
      "shares_30d_change": null,
      "pct_net_assets_today": 0.0051,
      "pct_net_assets_prior": 0.0051,
      "pct_net_assets_change": 0.0
    },
    {
      "ticker": "TSLA",
      "name": "TESLA INC COMMON STOCK USD.001",
      "status": "unchanged",
      "shares_today": 124459.0,
      "shares_prior": 124459.0,
      "shares_pct_change": 0.0,
      "shares_5d_change": 0.3953,
      "shares_10d_change": 1.0555,
      "shares_30d_change": null,
      "pct_net_assets_today": 0.0046,
      "pct_net_assets_prior": 0.0046,
      "pct_net_assets_change": 0.0
    },
    {
      "ticker": "TSM",
      "name": "TAIWAN SEMICONDUCTOR SP ADR ADR",
      "status": "unchanged",
      "shares_today": 515851.0,
      "shares_prior": 515851.0,
      "shares_pct_change": 0.0,
      "shares_5d_change": 0.4101,
      "shares_10d_change": 1.0955,
      "shares_30d_change": null,
      "pct_net_assets_today": 0.0205,
      "pct_net_assets_prior": 0.0204,
      "pct_net_assets_change": 0.0001
    },
    {
      "ticker": "UBER",
      "name": "UBER TECHNOLOGIES INC COMMON STOCK USD.00001",
      "status": "unchanged",
      "shares_today": 959190.0,
      "shares_prior": 959190.0,
      "shares_pct_change": 0.0,
      "shares_5d_change": 0.4104,
      "shares_10d_change": 1.0961,
      "shares_30d_change": null,
      "pct_net_assets_today": 0.0072,
      "pct_net_assets_prior": 0.007,
      "pct_net_assets_change": 0.0002
    },
    {
      "ticker": "UNH",
      "name": "UNITEDHEALTH GROUP INC COMMON STOCK USD.01",
      "status": "unchanged",
      "shares_today": 363086.0,
      "shares_prior": 363086.0,
      "shares_pct_change": 0.0,
      "shares_5d_change": 0.4065,
      "shares_10d_change": 1.0858,
      "shares_30d_change": null,
      "pct_net_assets_today": 0.0127,
      "pct_net_assets_prior": 0.0127,
      "pct_net_assets_change": 0.0
    },
    {
      "ticker": "URI",
      "name": "UNITED RENTALS INC COMMON STOCK USD.01",
      "status": "unchanged",
      "shares_today": 86528.0,
      "shares_prior": 86528.0,
      "shares_pct_change": 0.0,
      "shares_5d_change": 0.398,
      "shares_10d_change": 1.0629,
      "shares_30d_change": null,
      "pct_net_assets_today": 0.0082,
      "pct_net_assets_prior": 0.0083,
      "pct_net_assets_change": -0.0001
    },
    {
      "ticker": "V",
      "name": "VISA INC CLASS A SHARES COMMON STOCK USD.0001",
      "status": "unchanged",
      "shares_today": 217177.0,
      "shares_prior": 217177.0,
      "shares_pct_change": 0.0,
      "shares_5d_change": 0.4078,
      "shares_10d_change": 1.0892,
      "shares_30d_change": null,
      "pct_net_assets_today": 0.0066,
      "pct_net_assets_prior": 0.0066,
      "pct_net_assets_change": 0.0
    },
    {
      "ticker": "VICI",
      "name": "VICI PROPERTIES INC REIT USD.01",
      "status": "unchanged",
      "shares_today": 2240535.0,
      "shares_prior": 2240535.0,
      "shares_pct_change": 0.0,
      "shares_5d_change": 0.4106,
      "shares_10d_change": 1.0969,
      "shares_30d_change": null,
      "pct_net_assets_today": 0.0063,
      "pct_net_assets_prior": 0.0063,
      "pct_net_assets_change": 0.0
    },
    {
      "ticker": "VRTX",
      "name": "VERTEX PHARMACEUTICALS INC COMMON STOCK USD.01",
      "status": "unchanged",
      "shares_today": 374128.0,
      "shares_prior": 374128.0,
      "shares_pct_change": 0.0,
      "shares_5d_change": 0.4077,
      "shares_10d_change": 1.0889,
      "shares_30d_change": null,
      "pct_net_assets_today": 0.0157,
      "pct_net_assets_prior": 0.0158,
      "pct_net_assets_change": -0.0001
    },
    {
      "ticker": "WELL",
      "name": "WELLTOWER INC REIT USD1.0",
      "status": "unchanged",
      "shares_today": 310374.0,
      "shares_prior": 310374.0,
      "shares_pct_change": 0.0,
      "shares_5d_change": 0.4122,
      "shares_10d_change": 1.101,
      "shares_30d_change": null,
      "pct_net_assets_today": 0.0064,
      "pct_net_assets_prior": 0.0064,
      "pct_net_assets_change": 0.0
    },
    {
      "ticker": "WFC",
      "name": "WELLS FARGO + CO COMMON STOCK USD1.666",
      "status": "unchanged",
      "shares_today": 1477276.0,
      "shares_prior": 1477276.0,
      "shares_pct_change": 0.0,
      "shares_5d_change": 0.4097,
      "shares_10d_change": 1.0942,
      "shares_30d_change": null,
      "pct_net_assets_today": 0.0117,
      "pct_net_assets_prior": 0.0115,
      "pct_net_assets_change": 0.0002
    },
    {
      "ticker": "XOM",
      "name": "EXXON MOBIL CORP COMMON STOCK",
      "status": "unchanged",
      "shares_today": 588661.0,
      "shares_prior": 588661.0,
      "shares_pct_change": 0.0,
      "shares_5d_change": 0.4095,
      "shares_10d_change": 1.094,
      "shares_30d_change": null,
      "pct_net_assets_today": 0.0086,
      "pct_net_assets_prior": 0.0086,
      "pct_net_assets_change": 0.0
    },
    {
      "ticker": "XPO",
      "name": "XPO INC COMMON STOCK USD.001",
      "status": "unchanged",
      "shares_today": 481659.0,
      "shares_prior": 481659.0,
      "shares_pct_change": 0.0,
      "shares_5d_change": 0.4086,
      "shares_10d_change": 1.0914,
      "shares_30d_change": null,
      "pct_net_assets_today": 0.0104,
      "pct_net_assets_prior": 0.0106,
      "pct_net_assets_change": -0.0002
    }
  ]
}